baseobject/__init__.py
baseobject/_base.py
baseobject/_meta.py
baseobject/tests/__init__.py
baseobject/tests/test_base.py
baseobject-0.0.1.dist-info/LICENSE
baseobject-0.0.1.dist-info/METADATA
baseobject-0.0.1.dist-info/WHEEL
baseobject-0.0.1.dist-info/top_level.txt
baseobject-0.0.1.dist-info/RECORD
