Metadata-Version: 2.1
Name: baseobject
Version: 0.0.1
Summary: Base classes for sklearn-like parametric objects
Home-page: https://github.com/fkiraly/baseobject
Download-URL: https://pypi.org/project/baseobject/#files
Author: Markus Löning, Ryan Kuhns
Author-email: Franz Kiraly <f.kiraly@ucl.ac.uk>
Maintainer: Ryan Kuhns
Maintainer-email: Franz Kiraly <f.kiraly@ucl.ac.uk>
License: BSD 3-Clause License
Project-URL: homepage, https://github.com/fkiraly/baseobject
Project-URL: repository, https://github.com/fkiraly/baseobject
Project-URL: documentation, https://github.com/fkiraly/baseobject
Project-URL: download, https://pypi.org/project/baseobject/#files
Keywords: data-science,machine-learning,scikit-learn
Classifier: Intended Audience :: Science/Research
Classifier: Intended Audience :: Developers
Classifier: License :: OSI Approved :: BSD License
Classifier: Programming Language :: Python
Classifier: Topic :: Software Development
Classifier: Topic :: Scientific/Engineering
Classifier: Operating System :: Microsoft :: Windows
Classifier: Operating System :: POSIX
Classifier: Operating System :: Unix
Classifier: Operating System :: MacOS
Classifier: Programming Language :: Python :: 3.7
Classifier: Programming Language :: Python :: 3.8
Classifier: Programming Language :: Python :: 3.9
Requires-Python: >=3.7,<3.11
License-File: LICENSE
Requires-Dist: scikit-learn (<1.2.0,>=0.24.0)
Provides-Extra: dev
Requires-Dist: pytest ; extra == 'dev'
Requires-Dist: wheel ; extra == 'dev'
